{
  "id": "memory_1759440938253_n9aowzjv7",
  "timestamp": 1759440938253,
  "concept": "backpropagation",
  "embedding": [
    0.0723417094655868,
    0.10851256419838018,
    0,
    0,
    0,
    0,
    0,
    0,
    0,
    0,
    0,
    0,
    0,
    0,
    0,
    0,
    0.10851256419838018,
    0.12949165994340034,
    0,
    0,
    0,
    0,
    0,
    0,
    0.6508933001028103,
    0.09298475715754433,
    0.576316215906259,
    0,
    0,
    0,
    0,
    0
  ],
  "context": {
    "domain": "machine_learning",
    "difficulty": "intermediate"
  },
  "performance": 0.7,
  "confidence": 1,
  "relationships": [],
  "consolidated": false
}