{
  "id": "memory_1759535514936_igyav049u",
  "timestamp": 1759535514936,
  "concept": "code_quality_typescript",
  "embedding": [
    0.19042957753273096,
    0.14599600944176042,
    0,
    0,
    0,
    0,
    0,
    0,
    0,
    0,
    0,
    0,
    0,
    0,
    0,
    0,
    0.15869131461060912,
    0.1282225822053722,
    0,
    0,
    0,
    0,
    0,
    0,
    0.6311941969331094,
    0.18085135076793513,
    0.5288520133183863,
    0,
    0,
    0,
    0,
    0
  ],
  "context": {
    "domain": "code_quality",
    "type": "analysis"
  },
  "performance": 0.65,
  "confidence": 1,
  "relationships": [],
  "consolidated": false
}