{
  "id": "memory_1759440730557_1i0w25qzy",
  "timestamp": 1759440730557,
  "concept": "centralized_config",
  "embedding": [
    0.14486387107983917,
    0.13037748397185522,
    0,
    0,
    0,
    0,
    0,
    0,
    0,
    0,
    0,
    0,
    0,
    0,
    0,
    0,
    0.07243193553991958,
    0.05287531294414128,
    0,
    0,
    0,
    0,
    0,
    0,
    0.6499617028397155,
    0.09285167183424509,
    0.5769768959007072,
    0,
    0,
    0,
    0,
    0
  ],
  "context": {
    "domain": "system",
    "type": "learning"
  },
  "performance": 0.9,
  "confidence": 1,
  "relationships": [],
  "consolidated": false
}