{
  "id": "memory_1759445637395_95xnyf4au",
  "timestamp": 1759445637395,
  "concept": "advanced_analysis_typescript",
  "embedding": [
    0.19375824357831972,
    0.1808410273397651,
    0,
    0,
    0,
    0,
    0,
    0,
    0,
    0,
    0,
    0,
    0,
    0,
    0,
    0,
    0.1614652029819331,
    0.2454271085325383,
    0,
    0,
    0,
    0,
    0,
    0,
    0.6162393775699812,
    0.08803419679571159,
    0.5157012683969275,
    0,
    0,
    0,
    0,
    0
  ],
  "context": {
    "domain": "code_analysis",
    "type": "advanced_analysis",
    "timestamp": "2025-10-02T22:53:57.394Z"
  },
  "performance": 0.55,
  "confidence": 1,
  "relationships": [],
  "consolidated": false
}