{
  "id": "snapshot_1759440938368_general_concepts",
  "timestamp": 1759440938368,
  "domain": "general_concepts",
  "knowledgeGraph": {
    "nodes": [
      {
        "id": "memory_1759438895980_dowro45at",
        "concept": "node_user_service_node_class_UserService",
        "embedding": [
          0.29152123725724527,
          0.1943474915048302,
          0.48586872876207543,
          0.024293436438103774,
          0,
          0,
          0,
          0,
          0,
          0,
          0,
          0,
          0,
          0,
          0,
          0,
          0.24293436438103772,
          0.2390474145509411,
          0,
          0,
          0,
          0,
          0,
          0,
          0.42567487934027187,
          0.06081069704861026,
          0.3866885213622669,
          0,
          0,
          0,
          0,
          0
        ],
        "performance": 0.7,
        "confidence": 1
      },
      {
        "id": "memory_1759438896094_dy1p91887",
        "concept": "node_database_node_class_Database",
        "embedding": [
          0.2533025272991203,
          0.1671796680174194,
          0.5066050545982406,
          0.015351668321158805,
          0,
          0,
          0,
          0,
          0,
          0,
          0,
          0,
          0,
          0,
          0,
          0,
          0.2533025272991203,
          0.1823778196553666,
          0,
          0,
          0,
          0,
          0,
          0,
          0.44384286844610593,
          0.0634061240637294,
          0.4031919708068546,
          0,
          0,
          0,
          0,
          0
        ],
        "performance": 0.7,
        "confidence": 1
      },
      {
        "id": "memory_1759438896131_t6k36w14k",
        "concept": "class_generation_auth_service",
        "embedding": [
          0.22520432377983,
          0.16327313474037675,
          0,
          0,
          0,
          0,
          0,
          0,
          0,
          0,
          0,
          0,
          0,
          0,
          0,
          0,
          0.16890324283487249,
          0.5050206960762688,
          0,
          0,
          0,
          0,
          0,
          0,
          0.49326087947350766,
          0.0704658399247868,
          0.44808364989379107,
          0,
          0,
          0,
          0,
          0
        ],
        "performance": 1,
        "confidence": 1
      },
      {
        "id": "memory_1759438927206_lfpb5hink",
        "concept": "centralized_config",
        "embedding": [
          0.14672314484383536,
          0.1320508303594518,
          0,
          0,
          0,
          0,
          0,
          0,
          0,
          0,
          0,
          0,
          0,
          0,
          0,
          0,
          0.07336157242191768,
          0.0535539478679999,
          0,
          0,
          0,
          0,
          0,
          0,
          0.6429938125544695,
          0.09185625893635278,
          0.5838718489865179,
          0,
          0,
          0,
          0,
          0
        ],
        "performance": 0.9,
        "confidence": 1
      },
      {
        "id": "memory_1759438927208_3texfe2rt",
        "concept": "user_service",
        "embedding": [
          0.1454723641186632,
          0.08728341847119792,
          0,
          0,
          0,
          0,
          0,
          0,
          0,
          0,
          0,
          0,
          0,
          0,
          0,
          0,
          0.1454723641186632,
          0.10110329306247094,
          0,
          0,
          0,
          0,
          0,
          0,
          0.6375124817662625,
          0.09107321168089466,
          0.5788944785137511,
          0,
          0,
          0,
          0,
          0
        ],
        "performance": 0.8,
        "confidence": 1
      },
      {
        "id": "memory_1759438927225_3kqkp840h",
        "concept": "mcp_integration",
        "embedding": [
          0.14733229362428538,
          0.11049922021821401,
          0,
          0,
          0,
          0,
          0,
          0,
          0,
          0,
          0,
          0,
          0,
          0,
          0,
          0,
          0.07366614681214269,
          0.039043057810435614,
          0,
          0,
          0,
          0,
          0,
          0,
          0.6456635186180573,
          0.09223764551686531,
          0.5862959095136958,
          0,
          0,
          0,
          0,
          0
        ],
        "performance": 0.8,
        "confidence": 1
      }
    ],
    "edges": []
  },
  "embeddings": {},
  "relationships": [],
  "insights": [
    "Average performance: 0.817",
    "Concept diversity: 6 unique concepts",
    "Recent learning activity: 6 concepts learned"
  ],
  "confidence": 0.8166666666666665
}